flight_maneuvers/__about__.py
flight_maneuvers/__init__.py
flight_maneuvers/data_module.py
flight_maneuvers/neural_search.py
flight_maneuvers/utils.py
flight_maneuvers/modules/__init__.py
flight_maneuvers/modules/resnet.py
flight_maneuvers/modules/se2_resnet.py
flight_maneuvers/modules/se3_resnet.py
flight_maneuvers-1.0.1.dist-info/LICENSE
flight_maneuvers-1.0.1.dist-info/METADATA
flight_maneuvers-1.0.1.dist-info/WHEEL
flight_maneuvers-1.0.1.dist-info/top_level.txt
flight_maneuvers-1.0.1.dist-info/RECORD
