Metadata-Version: 2.1
Name: flight-maneuvers
Version: 1.0.1
Summary: A library for flight maneuver classification.
Home-page: https://github.com/clay-curry/Flight-Maneuvers
Download-URL: https://github.com/clay-curry/Flight-Maneuvers/archive/v1.0.1.tar.gz
Author: Clayton Curry
Author-email: claycurry34@gmail.com
License: BSD 3-Clause Clear
Keywords: pytorch,cnn,convolutional-networksequivariant,flight_manuevers
Requires-Python: >=3.7,<3.8
License-File: LICENSE
Requires-Dist: torch (>=1.3)
Requires-Dist: numpy
Requires-Dist: pandas
Requires-Dist: plotly
Requires-Dist: escnn
Requires-Dist: matplotlib
